db_faker/__init__.py
db_faker/cli.py
db_faker/cli_click.py
db_faker/commands/__init__.py
db_faker/commands/generate_data.py
db_faker/commands/validate_schema.py
db_faker/lib/__init__.py
db_faker/lib/output_handlers.py
db_faker/lib/schema.py
db_faker/lib/utils.py
db_faker/schemas/dbSchema.json
db_faker-0.1.1.dist-info/AUTHORS.rst
db_faker-0.1.1.dist-info/LICENSE
db_faker-0.1.1.dist-info/METADATA
db_faker-0.1.1.dist-info/WHEEL
db_faker-0.1.1.dist-info/entry_points.txt
db_faker-0.1.1.dist-info/top_level.txt
db_faker-0.1.1.dist-info/RECORD
