Metadata-Version: 2.1
Name: db-faker
Version: 0.1.1
Summary: CLI application that handles the creation of fake data to databases
Home-page: https://github.com/PBarri/db-faker
Author: Pablo Barrientos
License: MIT license
Keywords: db_faker test databases data
Platform: UNKNOWN
Classifier: Development Status :: 2 - Pre-Alpha
Classifier: Intended Audience :: Developers
Classifier: License :: OSI Approved :: MIT License
Classifier: Natural Language :: English
Classifier: Programming Language :: Python :: 3
Classifier: Programming Language :: Python :: 3.5
Classifier: Programming Language :: Python :: 3.6
Classifier: Programming Language :: Python :: 3.7
Classifier: Programming Language :: Python :: 3.8
Requires-Python: >=3.5
Requires-Dist: cliff (==3.4.0)
Requires-Dist: jsonschema (==3.2.0)
Requires-Dist: six (~=1.15.0)
Requires-Dist: Faker (~=4.1.2)
